<?xml version="1.0" encoding="UTF-8"?>
<!DOCTYPE ui:UiBinder SYSTEM "http://dl.google.com/gwt/DTD/xhtml.ent">
<ui:UiBinder xmlns:ui="urn:ui:com.google.gwt.uibinder" xmlns:g="urn:import:com.google.gwt.user.client.ui">

	<ui:style>
		@external .gwt-MenuBar;
		@external .gwt-MenuBar .gwt-MenuItem;
		@external .gwt-MenuBar .gwt-MenuItem-selected;
		.gwt-MenuBar {
			border: 1px solid #D3D3D3;
		    margin: 0 auto;
		    background-color: white;
		    font-size: 70%;
		    padding: 3px;
		}

		.gwt-MenuBar .gwt-MenuItem {
		    cursor: pointer;
		    background-color: white;
		    padding: 2px 10px;
		}

		.gwt-MenuBar .gwt-MenuItem-selected {
			background-color: #C3D0E0;
		}

		@external .gwt-PopupPanel;
		.gwt-PopupPanel {
		  border: 0px none;
		  padding: 0px;
		  background: white;
		  z-index: 1;
		}

		@external .gwt-MenuBarPopup;
		.gwt-MenuBarPopup {
		  z-index: 1;
		}

		@external .gwt-MenuBarPopup;
		.gwt-MenuBarPopup{
			margin: 0;
		}

		@external .gwt-MenuBarPopup .menuPopupMiddleLeft;
		.gwt-MenuBarPopup .menuPopupMiddleLeft {
			background: white;
		}

		@external .gwt-MenuBarPopup .menuPopupMiddleRight;
		.gwt-MenuBarPopup .menuPopupMiddleRight {
			background: white;
		}

		@external .gwt-MenuBarPopup .menuPopupTopCenter;
		.gwt-MenuBarPopup .menuPopupTopCenter {
			background: white;
		}

		@external .gwt-MenuBarPopup .menuPopupBottomCenter;
		.gwt-MenuBarPopup .menuPopupBottomCenter {
			background: white;
		}

		@external .gwt-MenuBarPopup .menuPopupTopLeftInner;
		.gwt-MenuBarPopup .menuPopupTopLeftInner {
			height: 0px;
			width: 0px;
		}

		@external .gwt-MenuBarPopup .menuPopupTopRightInner;
		.gwt-MenuBarPopup .menuPopupTopRightInner {
			height: 0px;
			width: 0px;
		}

		@external .gwt-MenuBarPopup .menuPopupBottomLeftInner;
		.gwt-MenuBarPopup .menuPopupBottomLeftInner {
			height: 0px;
			width: 0px;
		}

		@external .gwt-MenuBarPopup .menuPopupBottomRightInner;
		.gwt-MenuBarPopup .menuPopupBottomRightInner {
			height: 0px;
			width: 0px;
		}
		@external gwt-SplitLayoutPanel-HDragger;
		@external gwt-SplitLayoutPanel-VDragger;
		.gwt-SplitLayoutPanel-HDragger {
			background-color: #888888;
		}

		.gwt-SplitLayoutPanel-VDragger {
			background-color: #888888;
		}

		@external gwt-StackLayoutPanel .gwt-StackLayoutPanelHeader;
		@external gwt-StackLayoutPanel .gwt-StackLayoutPanelContent;
		.gwt-StackLayoutPanel .gwt-StackLayoutPanelHeader {
			font-family: Arial, sans-serif;
			font-size: 14px;
			color: #333333;
			padding-top: 0px;
			padding-left: 8px;
			border-top: 5px solid #f0f0f0;
			border-bottom: 1px solid #d5d5d5;
			border-left: 0px;
			border-right: 0px;
			background: #FFFFFF;
		}
		
		.gwt-StackLayoutPanel .gwt-StackLayoutPanelContent {
			border: 0px;
			padding: 2px;
		}
		
		.alertEventFooterPanel {
		}
	</ui:style>

	<g:DockLayoutPanel unit="PX">
		<g:north size="105">
			<g:SimplePanel ui:field="headerPanel" />
		</g:north>

		<g:center>
			<g:SplitLayoutPanel ui:field="verticalSplitLayoutPanel">
				<g:center>
					<g:SplitLayoutPanel ui:field="horizontalSplitLayoutPanel">
						<g:west size="235">
							<g:StackLayoutPanel ui:field="westStackPanel" />
						</g:west>

						<g:center>
							<g:LayoutPanel ui:field="mainContentPanel" />
						</g:center>
					</g:SplitLayoutPanel>
				</g:center>
				<g:south size="26">
					<g:SimplePanel ui:field="alertEventFooterPanel" addStyleNames="{style.alertEventFooterPanel}" />
				</g:south>
			</g:SplitLayoutPanel>
		</g:center>
	</g:DockLayoutPanel>

</ui:UiBinder>
